tomato_picovna/__init__.py
tomato_picovna-2.1.0.dist-info/licenses/LICENSE
tomato_picovna-2.1.0.dist-info/METADATA
tomato_picovna-2.1.0.dist-info/WHEEL
tomato_picovna-2.1.0.dist-info/top_level.txt
tomato_picovna-2.1.0.dist-info/RECORD
