Metadata-Version: 2.4
Name: tomato-picovna
Version: 2.1.0
Summary: This package is a part of tomato. It has been made for the automation of PicoVNA network analysers.
Author-email: Peter Kraus <peter.kraus@ceramics.tu-berlin.de>
Project-URL: Homepage, https://github.com/dgbowl/tomato-picovna
Project-URL: Bug Tracker, https://github.com/dgbowl/tomato-picovna/issues
Classifier: Development Status :: 3 - Alpha
Classifier: License :: OSI Approved :: GNU General Public License v3 or later (GPLv3+)
Classifier: Programming Language :: Python :: 3.10
Classifier: Programming Language :: Python :: 3.11
Classifier: Operating System :: OS Independent
Requires-Python: <3.12,>=3.10
License-File: LICENSE
Requires-Dist: vna>=0.0.5
Requires-Dist: psutil>=5.9
Requires-Dist: tomato>=2.1rc3
Provides-Extra: testing
Requires-Dist: pytest; extra == "testing"
Dynamic: license-file
